Abhi_pdf-8.0.dist-info/DESCRIPTION.rst
Abhi_pdf-8.0.dist-info/METADATA
Abhi_pdf-8.0.dist-info/RECORD
Abhi_pdf-8.0.dist-info/WHEEL
Abhi_pdf-8.0.dist-info/metadata.json
Abhi_pdf-8.0.dist-info/top_level.txt
abhi_pdf/__init__.py
