Metadata-Version: 2.0
Name: Abhi-pdf
Version: 8.0
Summary: Testing the efficientcy of Inspector
Home-page: UNKNOWN
Author: Tector Pro
Author-email: UNKNOWN
License: UNKNOWN
Platform: UNKNOWN
